pytest_discover/__about__.py
pytest_discover/__about__.pyi
pytest_discover/__init__.py
pytest_discover/plugin.py
pytest_discover/py.typed
pytest_discover/internal/__init__.py
pytest_discover/internal/_fields.py
pytest_discover/internal/_utils.py
pytest_discover/models/__init__.py
pytest_discover/models/collect_report.py
pytest_discover/models/discovery_event.py
pytest_discover/models/discovery_result.py
pytest_discover/models/error_message.py
pytest_discover/models/session_finish.py
pytest_discover/models/session_start.py
pytest_discover/models/test_item.py
pytest_discover/models/warning_message.py
pytest_discover-0.4.0.dist-info/METADATA
pytest_discover-0.4.0.dist-info/WHEEL
pytest_discover-0.4.0.dist-info/entry_points.txt
pytest_discover-0.4.0.dist-info/RECORD
