Metadata-Version: 2.3
Name: pytest-discover
Version: 0.4.0
Summary: Pytest plugin to record discovered tests in a file
Project-URL: Source, https://github.com/charbonnierg/pytest-discover
Project-URL: Tracker, https://github.com/charbonnierg/pytest-discover/issues
Author-email: Guillaume Charbonnier <gu.charbon@gmail.com>
Requires-Python: >=3.8
Requires-Dist: pytest
